steelpy/__init__.py
steelpy/shape files/C_shapes.csv
steelpy/shape files/DBL_L_shapes.csv
steelpy/shape files/HP_shapes.csv
steelpy/shape files/HSS_R_shapes.csv
steelpy/shape files/HSS_shapes.csv
steelpy/shape files/L_shapes.csv
steelpy/shape files/M_shapes.csv
steelpy/shape files/MC_shapes.csv
steelpy/shape files/MT_shapes.csv
steelpy/shape files/PIPE_shapes.csv
steelpy/shape files/S_shapes.csv
steelpy/shape files/ST_shapes.csv
steelpy/shape files/W_shapes.csv
steelpy/shape files/WT_shapes.csv
steelpy/steelpy.py
steelpy-1.1.0.dist-info/license.txt
steelpy-1.1.0.dist-info/METADATA
steelpy-1.1.0.dist-info/WHEEL
steelpy-1.1.0.dist-info/RECORD
