Metadata-Version: 2.1
Name: steelpy
Version: 1.1.0
Summary: A simple library for section properties of AISC steel shapes
License: Apache-2.0
Keywords: steel,AISC,engineering,shapes_AISC,AISC Shapes Database v16.0
Author: evanfaler
Author-email: emfaler@gmail.com
Requires-Python: >=3.9,<4.0
Classifier: License :: OSI Approved :: Apache Software License
Classifier: Programming Language :: Python :: 3
Classifier: Programming Language :: Python :: 3.9
Classifier: Programming Language :: Python :: 3.10
Classifier: Programming Language :: Python :: 3.11
Classifier: Programming Language :: Python :: 3.12
Requires-Dist: openpyxl (>=3.1.2,<4.0.0)
Requires-Dist: pandas (>=2.2.2,<3.0.0)
